pyknit/Chart.py
pyknit/GaugeSwatch.py
pyknit/Hat.py
pyknit/Sock.py
pyknit/Stitches.py
pyknit/__init__.py
pyknit/__main__.py
pyknit/pi_shawl.py
pyknit-0.0.9.dist-info/LICENSE
pyknit-0.0.9.dist-info/METADATA
pyknit-0.0.9.dist-info/WHEEL
pyknit-0.0.9.dist-info/entry_points.txt
pyknit-0.0.9.dist-info/top_level.txt
pyknit-0.0.9.dist-info/RECORD
