Metadata-Version: 2.1
Name: pyknit
Version: 0.0.9
Summary: A set of math and charting tools for knitters.
Author-email: Terri Oda <terri@toybox.ca>
License: GNU GENERAL PUBLIC LICENSE
Project-URL: Homepage, https://github.com/terriko/pyknit
Project-URL: Bug Tracker, https://github.com/terriko/pyknit/issues
Classifier: Development Status :: 1 - Planning
Classifier: Programming Language :: Python :: 3
Classifier: License :: OSI Approved :: GNU General Public License v2 or later (GPLv2+)
Classifier: Operating System :: OS Independent
Requires-Python: >=3.9
License-File: LICENSE
